easyconvert/__init__.py
easyconvert/easyconvert.py
easyconvert-0.1.0.dist-info/licenses/LICENSE
easyconvert-0.1.0.dist-info/METADATA
easyconvert-0.1.0.dist-info/WHEEL
easyconvert-0.1.0.dist-info/top_level.txt
easyconvert-0.1.0.dist-info/RECORD
