Metadata-Version: 2.4
Name: easyconvert
Version: 0.1.0
Summary: A simple unit conversion library for Python.
Home-page: https://github.com/yourusername/easyconvert
Author: Rafsan
Classifier: Programming Language :: Python :: 3
Classifier: License :: OSI Approved :: MIT License
Classifier: Operating System :: OS Independent
Requires-Python: >=3.6
License-File: LICENSE
Dynamic: author
Dynamic: classifier
Dynamic: description-content-type
Dynamic: home-page
Dynamic: license-file
Dynamic: requires-python
Dynamic: summary
